snipsowm/__init__.py
snipsowm/snipsowm.py
snipsowm-0.1.3.dist-info/DESCRIPTION.rst
snipsowm-0.1.3.dist-info/METADATA
snipsowm-0.1.3.dist-info/RECORD
snipsowm-0.1.3.dist-info/WHEEL
snipsowm-0.1.3.dist-info/metadata.json
snipsowm-0.1.3.dist-info/top_level.txt
