Metadata-Version: 2.0
Name: snipsowm
Version: 0.1.3
Summary: OpenWeatherMap weather skill for Snips
Home-page: https://github.com/snipsco/snips-skill-owm
Author: Michael Fester
Author-email: michael.fester@gmail.com
License: MIT
Keywords: snips
Platform: UNKNOWN
Requires-Dist: requests (==2.6.0)
